monasca_common/__init__.py
monasca_common/confluent_kafka/__init__.py
monasca_common/confluent_kafka/consumer.py
monasca_common/confluent_kafka/producer.py
monasca_common/healthcheck/__init__.py
monasca_common/healthcheck/result.py
monasca_common/healthcheck/checks/__init__.py
monasca_common/healthcheck/checks/kafka_check.py
monasca_common/kafka/__init__.py
monasca_common/kafka/client_factory.py
monasca_common/kafka/consumer.py
monasca_common/kafka/legacy_kafka_consumer.py
monasca_common/kafka/legacy_kafka_message.py
monasca_common/kafka/producer.py
monasca_common/kafka_lib/NOTES.md
monasca_common/kafka_lib/__init__.py
monasca_common/kafka_lib/client.py
monasca_common/kafka_lib/codec.py
monasca_common/kafka_lib/common.py
monasca_common/kafka_lib/conn.py
monasca_common/kafka_lib/context.py
monasca_common/kafka_lib/protocol.py
monasca_common/kafka_lib/util.py
monasca_common/kafka_lib/version.py
monasca_common/kafka_lib/consumer/__init__.py
monasca_common/kafka_lib/consumer/base.py
monasca_common/kafka_lib/consumer/kafka.py
monasca_common/kafka_lib/consumer/multiprocess.py
monasca_common/kafka_lib/consumer/simple.py
monasca_common/kafka_lib/partitioner/__init__.py
monasca_common/kafka_lib/partitioner/base.py
monasca_common/kafka_lib/partitioner/hashed.py
monasca_common/kafka_lib/partitioner/roundrobin.py
monasca_common/kafka_lib/producer/__init__.py
monasca_common/kafka_lib/producer/base.py
monasca_common/kafka_lib/producer/keyed.py
monasca_common/kafka_lib/producer/simple.py
monasca_common/monasca_query_language/__init__.py
monasca_common/monasca_query_language/aql_parser.py
monasca_common/monasca_query_language/exceptions.py
monasca_common/monasca_query_language/query_structures.py
monasca_common/policy/__init__.py
monasca_common/policy/i18n.py
monasca_common/policy/policy_engine.py
monasca_common/repositories/__init__.py
monasca_common/repositories/constants.py
monasca_common/repositories/exceptions.py
monasca_common/repositories/mysql/__init__.py
monasca_common-3.8.0.dist-info/AUTHORS
monasca_common-3.8.0.dist-info/LICENSE
monasca_common-3.8.0.dist-info/METADATA
monasca_common-3.8.0.dist-info/WHEEL
monasca_common-3.8.0.dist-info/pbr.json
monasca_common-3.8.0.dist-info/top_level.txt
monasca_common-3.8.0.dist-info/RECORD
