Metadata-Version: 2.1
Name: monasca-common
Version: 3.8.0
Summary: Monasca common python modules
Home-page: https://opendev.org/openstack/monasca-common
Author: OpenStack
Author-email: openstack-discuss@lists.openstack.org
License: UNKNOWN
Platform: UNKNOWN
Classifier: Intended Audience :: Information Technology
Classifier: Intended Audience :: System Administrators
Classifier: License :: OSI Approved :: Apache Software License
Classifier: Operating System :: POSIX :: Linux
Classifier: Programming Language :: Python
Classifier: Programming Language :: Python :: Implementation :: CPython
Classifier: Programming Language :: Python :: 3 :: Only
Classifier: Programming Language :: Python :: 3
Classifier: Programming Language :: Python :: 3.6
Classifier: Programming Language :: Python :: 3.7
Classifier: Programming Language :: Python :: 3.8
Requires-Python: >=3.6
Requires-Dist: PyMySQL (>=0.8.0)
Requires-Dist: confluent-kafka (>=1.3.0)
Requires-Dist: kazoo (>=2.8.0)
Requires-Dist: oslo.config (>=6.8.0)
Requires-Dist: oslo.policy (>=3.6.0)
Requires-Dist: pbr (!=2.1.0,>=2.0.0)
Requires-Dist: pyparsing (>=2.1.0)
Requires-Dist: simplejson (>=3.13.2)
